devpilot/__init__.py
devpilot/__main__.py
devpilot/constants.py
devpilot/detect_lang.py
devpilot/explain.py
devpilot/interactive.py
devpilot/log_utils.py
devpilot/ollama_infer.py
devpilot/onboard.py
devpilot/onboarder.py
devpilot/prompt.py
devpilot/prompt_helpers.py
devpilot/refactor.py
devpilot/rel_map.py
devpilot/repomap_utils.py
devpilot/session_logger.py
devpilot_hq-1.0.2.dist-info/licenses/LICENSE
devpilot_hq-1.0.2.dist-info/METADATA
devpilot_hq-1.0.2.dist-info/WHEEL
devpilot_hq-1.0.2.dist-info/entry_points.txt
devpilot_hq-1.0.2.dist-info/top_level.txt
devpilot_hq-1.0.2.dist-info/RECORD
