Metadata-Version: 2.4
Name: devpilot-hq
Version: 1.0.2
Summary: AI-powered CLI for onboarding, explaining, and refactoring legacy codebases.
Author-email: Sandeeb Adhikari <adhikarisandeeb@gmail.com>
License: MIT
Project-URL: Homepage, https://github.com/SandeebAdhikari/DevPilot-HQ
Project-URL: Issues, https://github.com/SandeebAdhikari/DevPilot-HQ/issues
Project-URL: Changelog, https://github.com/SandeebAdhikari/DevPilot-HQ/releases
Classifier: Programming Language :: Python :: 3
Classifier: License :: OSI Approved :: MIT License
Requires-Python: >=3.7
License-File: LICENSE
Requires-Dist: rich
Requires-Dist: requests
Provides-Extra: dev
Requires-Dist: pytest; extra == "dev"
Dynamic: license-file
